pynth/__about__.py
pynth/__init__.py
pynth/audio_compiler.py
pynth/const.py
pynth/effect.py
pynth/instrument.py
pynth/let.py
pynth/note.py
pynth/oscillator.py
pynth/score.py
pynth/tempo.py
pynth/tools.py
pynth-0.0.3.dist-info/METADATA
pynth-0.0.3.dist-info/WHEEL
pynth-0.0.3.dist-info/licenses/LICENSE.txt
pynth-0.0.3.dist-info/RECORD
