Metadata-Version: 2.1
Name: pynth
Version: 0.0.3
Project-URL: Documentation, https://github.com/dulong-lab/pynth#readme
Project-URL: Issues, https://github.com/dulong-lab/pynth/issues
Project-URL: Source, https://github.com/dulong-lab/pynth
Author-email: dulong-lab <dulong-lab@outlook.com>
License-File: LICENSE.txt
Classifier: Development Status :: 2 - Pre-Alpha
Classifier: Programming Language :: Python
Classifier: Programming Language :: Python :: 3.7
Classifier: Programming Language :: Python :: 3.8
Classifier: Programming Language :: Python :: 3.9
Classifier: Programming Language :: Python :: 3.10
Classifier: Programming Language :: Python :: 3.11
Classifier: Programming Language :: Python :: Implementation :: CPython
Classifier: Programming Language :: Python :: Implementation :: PyPy
Requires-Python: >=3.7
Requires-Dist: matplotlib
Requires-Dist: numpy
